src/ALU_8bit.v
module ALU_8bit(
    input [7:0] A,
    input [7:0] B,
    input [2:0] Opcode,
    input Carry_in,
    output reg [7:0] Result,
    output reg Carry_out,
    output Zero,
    output Negative
);
    
    // Temporary 9-bit register for arithmetic operations to capture carry
    reg [8:0] temp;
    
    // Zero flag (combinational)
    assign Zero = (Result == 8'b0);
    
    // Negative flag (combinational)
    assign Negative = Result[7];
    
    always @(*) begin
        case(Opcode)
            3'b000: begin // ADD
                temp = A + B + Carry_in;
                Result = temp[7:0];
                Carry_out = temp[8];
            end
            
            3'b001: begin // SUB
                temp = A - B;
                Result = temp[7:0];
                Carry_out = temp[8];
            end
            
            3'b010: begin // AND
                Result = A & B;
                Carry_out = 0;
            end
            
            3'b011: begin // OR
                Result = A | B;
                Carry_out = 0;
            end
            
            3'b100: begin // XOR
                Result = A ^ B;
                Carry_out = 0;
            end
            
            3'b101: begin // NOT
                Result = ~A;
                Carry_out = 0;
            end
            
            3'b110: begin // SHL (Logical Shift Left)
                {Carry_out, Result} = {A, 1'b0};
            end
            
            3'b111: begin // SHR (Logical Shift Right)
                {Result, Carry_out} = {1'b0, A};
            end
            
            default: begin
                Result = 8'b0;
                Carry_out = 0;
            end
        endcase
    end
endmodule

src/ALU_8bit_tb.v
module ALU_8bit_tb;
    reg [7:0] A, B;
    reg [2:0] Opcode;
    reg Carry_in;
    wire [7:0] Result;
    wire Carry_out, Zero, Negative;
    
    ALU_8bit uut(
        .A(A),
        .B(B),
        .Opcode(Opcode),
        .Carry_in(Carry_in),
        .Result(Result),
        .Carry_out(Carry_out),
        .Zero(Zero),
        .Negative(Negative)
    );
    
    initial begin
        // Initialize VCD file dumping
        $dumpfile("ALU_8bit_tb.vcd");
        $dumpvars(0, ALU_8bit_tb);
        
        // Test ADD
        A = 8'h55; B = 8'hAA; Opcode = 3'b000; Carry_in = 0;
        #10 $display("ADD: %h + %h = %h, Carry=%b, Zero=%b, Negative=%b", A, B, Result, Carry_out, Zero, Negative);
        
        // Test ADD with carry
        A = 8'hFF; B = 8'h01; Opcode = 3'b000; Carry_in = 0;
        #10 $display("ADD: %h + %h = %h, Carry=%b, Zero=%b, Negative=%b", A, B, Result, Carry_out, Zero, Negative);
        
        // Test SUB
        A = 8'h55; B = 8'h10; Opcode = 3'b001; Carry_in = 0;
        #10 $display("SUB: %h - %h = %h, Carry=%b, Zero=%b, Negative=%b", A, B, Result, Carry_out, Zero, Negative);
        
        // Test AND
        A = 8'h55; B = 8'h0F; Opcode = 3'b010; Carry_in = 0;
        #10 $display("AND: %h & %h = %h, Carry=%b, Zero=%b, Negative=%b", A, B, Result, Carry_out, Zero, Negative);
        
        // Test OR
        A = 8'h55; B = 8'h0F; Opcode = 3'b011; Carry_in = 0;
        #10 $display("OR: %h | %h = %h, Carry=%b, Zero=%b, Negative=%b", A, B, Result, Carry_out, Zero, Negative);
        
        // Test XOR
        A = 8'h55; B = 8'hFF; Opcode = 3'b100; Carry_in = 0;
        #10 $display("XOR: %h ^ %h = %h, Carry=%b, Zero=%b, Negative=%b", A, B, Result, Carry_out, Zero, Negative);
        
        // Test NOT
        A = 8'h55; Opcode = 3'b101; Carry_in = 0;
        #10 $display("NOT: ~%h = %h, Carry=%b, Zero=%b, Negative=%b", A, Result, Carry_out, Zero, Negative);
        
        // Test SHL (Shift Left)
        A = 8'b10101010; Opcode = 3'b110; Carry_in = 0;
        #10 $display("SHL: %b << 1 = %b, Carry=%b, Zero=%b, Negative=%b", A, Result, Carry_out, Zero, Negative);
        
        // Test SHR (Shift Right)
        A = 8'b10101010; Opcode = 3'b111; Carry_in = 0;
        #10 $display("SHR: %b >> 1 = %b, Carry=%b, Zero=%b, Negative=%b", A, Result, Carry_out, Zero, Negative);
        
        $finish;
    end
endmodule

simulations/waveforms/ALU_8bit_tb.vcd
$date
	Fri Apr 18 23:16:00 2025
$end
$version
	Icarus Verilog
$end
$timescale
	1s
$end
$scope module ALU_8bit_tb $end
$var wire 1 ! Zero $end
$var wire 8 " Result [7:0] $end
$var wire 1 # Negative $end
$var wire 1 $ Carry_out $end
$var reg 8 % A [7:0] $end
$var reg 8 & B [7:0] $end
$var reg 1 ' Carry_in $end
$var reg 3 ( Opcode [2:0] $end
$scope module uut $end
$var wire 8 ) A [7:0] $end
$var wire 8 * B [7:0] $end
$var wire 1 ' Carry_in $end
$var wire 3 + Opcode [2:0] $end
$var wire 1 ! Zero $end
$var wire 1 # Negative $end
$var reg 1 $ Carry_out $end
$var reg 8 , Result [7:0] $end
$var reg 9 - temp [8:0] $end
$upscope $end
$upscope $end
$enddefinitions $end
#0
$dumpvars
b11111111 -
b11111111 ,
b0 +
b10101010 *
b1010101 )
b0 (
0'
b10101010 &
b1010101 %
0$
1#
b11111111 "
0!
$end
#10
0#
1$
1!
b0 "
b0 ,
b100000000 -
b1 &
b1 *
b11111111 %
b11111111 )
#20
0$
0!
b1000101 "
b1000101 ,
b1000101 -
b1 (
b1 +
b10000 &
b10000 *
b1010101 %
b1010101 )
#30
b101 "
b101 ,
b10 (
b10 +
b1111 &
b1111 *
#40
b1011111 "
b1011111 ,
b11 (
b11 +
#50
1#
b10101010 "
b10101010 ,
b100 (
b100 +
b11111111 &
b11111111 *
#60
b101 (
b101 +
#70
0#
1$
b1010100 "
b1010100 ,
b110 (
b110 +
b10101010 %
b10101010 )
#80
b1010101 "
b1010101 ,
0$
b111 (
b111 +
